{
  "meta": {
    "generated_at": "2026-03-08 18:30:06",
    "latest_days": 14,
    "count": 336
  },
  "readings": [
    {
      "sensor_id": "plant1",
      "ts": "2026-02-22 18:00:00",
      "raw": 632.0,
      "moisture": 100.0,
      "vcc": null,
      "rssi": -65.0
    },
    {
      "sensor_id": "plant1",
      "ts": "2026-02-22 19:00:00",
      "raw": 631.5,
      "moisture": 100.0,
      "vcc": null,
      "rssi": -65.0
    },
    {
      "sensor_id": "plant1",
      "ts": "2026-02-22 20:00:00",
      "raw": 631.75,
      "moisture": 100.0,
      "vcc": null,
      "rssi": -65.0
    },
    {
      "sensor_id": "plant1",
      "ts": "2026-02-22 21:00:00",
      "raw": 631.5,
      "moisture": 99.75,
      "vcc": null,
      "rssi": -65.0
    },
    {
      "sensor_id": "plant1",
      "ts": "2026-02-22 22:00:00",
      "raw": 631.25,
      "moisture": 100.0,
      "vcc": null,
      "rssi": -65.0
    },
    {
      "sensor_id": "plant1",
      "ts": "2026-02-22 23:00:00",
      "raw": 630.75,
      "moisture": 99.75,
      "vcc": null,
      "rssi": -65.0
    },
    {
      "sensor_id": "plant1",
      "ts": "2026-02-23 00:00:00",
      "raw": 630.75,
      "moisture": 99.75,
      "vcc": null,
      "rssi": -65.0
    },
    {
      "sensor_id": "plant1",
      "ts": "2026-02-23 01:00:00",
      "raw": 629.5,
      "moisture": 99.5,
      "vcc": null,
      "rssi": -65.0
    },
    {
      "sensor_id": "plant1",
      "ts": "2026-02-23 02:00:00",
      "raw": 630.5,
      "moisture": 99.5,
      "vcc": null,
      "rssi": -65.0
    },
    {
      "sensor_id": "plant1",
      "ts": "2026-02-23 03:00:00",
      "raw": 630.0,
      "moisture": 99.25,
      "vcc": null,
      "rssi": -65.0
    },
    {
      "sensor_id": "plant1",
      "ts": "2026-02-23 04:00:00",
      "raw": 630.5,
      "moisture": 99.75,
      "vcc": null,
      "rssi": -65.0
    },
    {
      "sensor_id": "plant1",
      "ts": "2026-02-23 05:00:00",
      "raw": 630.5,
      "moisture": 99.75,
      "vcc": null,
      "rssi": -64.75
    },
    {
      "sensor_id": "plant1",
      "ts": "2026-02-23 06:00:00",
      "raw": 635.25,
      "moisture": 100.0,
      "vcc": null,
      "rssi": -64.25
    },
    {
      "sensor_id": "plant1",
      "ts": "2026-02-23 07:00:00",
      "raw": 631.75,
      "moisture": 100.0,
      "vcc": null,
      "rssi": -64.75
    },
    {
      "sensor_id": "plant1",
      "ts": "2026-02-23 08:00:00",
      "raw": 630.5,
      "moisture": 99.75,
      "vcc": null,
      "rssi": -64.75
    },
    {
      "sensor_id": "plant1",
      "ts": "2026-02-23 09:00:00",
      "raw": 629.75,
      "moisture": 99.5,
      "vcc": null,
      "rssi": -65.0
    },
    {
      "sensor_id": "plant1",
      "ts": "2026-02-23 10:00:00",
      "raw": 630.75,
      "moisture": 100.0,
      "vcc": null,
      "rssi": -65.0
    },
    {
      "sensor_id": "plant1",
      "ts": "2026-02-23 11:00:00",
      "raw": 628.75,
      "moisture": 99.0,
      "vcc": null,
      "rssi": -65.0
    },
    {
      "sensor_id": "plant1",
      "ts": "2026-02-23 12:00:00",
      "raw": 629.75,
      "moisture": 99.25,
      "vcc": null,
      "rssi": -65.0
    },
    {
      "sensor_id": "plant1",
      "ts": "2026-02-23 13:00:00",
      "raw": 628.5,
      "moisture": 99.0,
      "vcc": null,
      "rssi": -65.0
    },
    {
      "sensor_id": "plant1",
      "ts": "2026-02-23 14:00:00",
      "raw": 629.8,
      "moisture": 99.4,
      "vcc": null,
      "rssi": -65.0
    },
    {
      "sensor_id": "plant1",
      "ts": "2026-02-23 15:00:00",
      "raw": 628.0,
      "moisture": 98.75,
      "vcc": null,
      "rssi": -65.0
    },
    {
      "sensor_id": "plant1",
      "ts": "2026-02-23 16:00:00",
      "raw": 629.25,
      "moisture": 99.25,
      "vcc": null,
      "rssi": -65.0
    },
    {
      "sensor_id": "plant1",
      "ts": "2026-02-23 17:00:00",
      "raw": 630.25,
      "moisture": 99.75,
      "vcc": null,
      "rssi": -64.25
    },
    {
      "sensor_id": "plant1",
      "ts": "2026-02-23 18:00:00",
      "raw": 628.5,
      "moisture": 99.0,
      "vcc": null,
      "rssi": -64.75
    },
    {
      "sensor_id": "plant1",
      "ts": "2026-02-23 19:00:00",
      "raw": 631.5,
      "moisture": 99.75,
      "vcc": null,
      "rssi": -64.5
    },
    {
      "sensor_id": "plant1",
      "ts": "2026-02-23 20:00:00",
      "raw": 631.25,
      "moisture": 100.0,
      "vcc": null,
      "rssi": -64.25
    },
    {
      "sensor_id": "plant1",
      "ts": "2026-02-23 21:00:00",
      "raw": 629.0,
      "moisture": 99.25,
      "vcc": null,
      "rssi": -65.25
    },
    {
      "sensor_id": "plant1",
      "ts": "2026-02-23 22:00:00",
      "raw": 629.0,
      "moisture": 99.25,
      "vcc": null,
      "rssi": -64.75
    },
    {
      "sensor_id": "plant1",
      "ts": "2026-02-23 23:00:00",
      "raw": 630.0,
      "moisture": 99.5,
      "vcc": null,
      "rssi": -65.0
    },
    {
      "sensor_id": "plant1",
      "ts": "2026-02-24 00:00:00",
      "raw": 630.0,
      "moisture": 99.5,
      "vcc": null,
      "rssi": -65.0
    },
    {
      "sensor_id": "plant1",
      "ts": "2026-02-24 01:00:00",
      "raw": 631.5,
      "moisture": 99.75,
      "vcc": null,
      "rssi": -64.5
    },
    {
      "sensor_id": "plant1",
      "ts": "2026-02-24 02:00:00",
      "raw": 628.75,
      "moisture": 99.0,
      "vcc": null,
      "rssi": -65.0
    },
    {
      "sensor_id": "plant1",
      "ts": "2026-02-24 03:00:00",
      "raw": 629.75,
      "moisture": 99.5,
      "vcc": null,
      "rssi": -65.0
    },
    {
      "sensor_id": "plant1",
      "ts": "2026-02-24 04:00:00",
      "raw": 630.25,
      "moisture": 99.5,
      "vcc": null,
      "rssi": -65.0
    },
    {
      "sensor_id": "plant1",
      "ts": "2026-02-24 05:00:00",
      "raw": 629.0,
      "moisture": 99.25,
      "vcc": null,
      "rssi": -65.0
    },
    {
      "sensor_id": "plant1",
      "ts": "2026-02-24 06:00:00",
      "raw": 626.5,
      "moisture": 97.75,
      "vcc": null,
      "rssi": -65.0
    },
    {
      "sensor_id": "plant1",
      "ts": "2026-02-24 07:00:00",
      "raw": 630.75,
      "moisture": 99.75,
      "vcc": null,
      "rssi": -64.75
    },
    {
      "sensor_id": "plant1",
      "ts": "2026-02-24 08:00:00",
      "raw": 630.75,
      "moisture": 99.75,
      "vcc": null,
      "rssi": -64.5
    },
    {
      "sensor_id": "plant1",
      "ts": "2026-02-24 09:00:00",
      "raw": 628.75,
      "moisture": 99.25,
      "vcc": null,
      "rssi": -65.0
    },
    {
      "sensor_id": "plant1",
      "ts": "2026-02-24 10:00:00",
      "raw": 629.5,
      "moisture": 99.25,
      "vcc": null,
      "rssi": -65.0
    },
    {
      "sensor_id": "plant1",
      "ts": "2026-02-24 11:00:00",
      "raw": 627.25,
      "moisture": 98.5,
      "vcc": null,
      "rssi": -65.0
    },
    {
      "sensor_id": "plant1",
      "ts": "2026-02-24 12:00:00",
      "raw": 627.5,
      "moisture": 98.5,
      "vcc": null,
      "rssi": -65.0
    },
    {
      "sensor_id": "plant1",
      "ts": "2026-02-24 13:00:00",
      "raw": 628.5,
      "moisture": 99.0,
      "vcc": null,
      "rssi": -65.0
    },
    {
      "sensor_id": "plant1",
      "ts": "2026-02-24 14:00:00",
      "raw": 627.75,
      "moisture": 98.75,
      "vcc": null,
      "rssi": -65.0
    },
    {
      "sensor_id": "plant1",
      "ts": "2026-02-24 15:00:00",
      "raw": 626.75,
      "moisture": 98.25,
      "vcc": null,
      "rssi": -65.0
    },
    {
      "sensor_id": "plant1",
      "ts": "2026-02-24 16:00:00",
      "raw": 629.0,
      "moisture": 99.0,
      "vcc": null,
      "rssi": -65.0
    },
    {
      "sensor_id": "plant1",
      "ts": "2026-02-24 17:00:00",
      "raw": 628.5,
      "moisture": 98.75,
      "vcc": null,
      "rssi": -64.5
    },
    {
      "sensor_id": "plant1",
      "ts": "2026-02-24 18:00:00",
      "raw": 627.0,
      "moisture": 98.25,
      "vcc": null,
      "rssi": -64.5
    },
    {
      "sensor_id": "plant1",
      "ts": "2026-02-24 19:00:00",
      "raw": 627.5,
      "moisture": 98.5,
      "vcc": null,
      "rssi": -64.75
    },
    {
      "sensor_id": "plant1",
      "ts": "2026-02-24 20:00:00",
      "raw": 629.0,
      "moisture": 99.25,
      "vcc": null,
      "rssi": -64.75
    },
    {
      "sensor_id": "plant1",
      "ts": "2026-02-24 21:00:00",
      "raw": 628.25,
      "moisture": 99.0,
      "vcc": null,
      "rssi": -65.0
    },
    {
      "sensor_id": "plant1",
      "ts": "2026-02-24 22:00:00",
      "raw": 629.0,
      "moisture": 99.5,
      "vcc": null,
      "rssi": -64.75
    },
    {
      "sensor_id": "plant1",
      "ts": "2026-02-24 23:00:00",
      "raw": 628.5,
      "moisture": 99.0,
      "vcc": null,
      "rssi": -64.75
    },
    {
      "sensor_id": "plant1",
      "ts": "2026-02-25 00:00:00",
      "raw": 628.75,
      "moisture": 99.0,
      "vcc": null,
      "rssi": -64.5
    },
    {
      "sensor_id": "plant1",
      "ts": "2026-02-25 01:00:00",
      "raw": 629.25,
      "moisture": 99.5,
      "vcc": null,
      "rssi": -64.5
    },
    {
      "sensor_id": "plant1",
      "ts": "2026-02-25 02:00:00",
      "raw": 630.75,
      "moisture": 100.0,
      "vcc": null,
      "rssi": -64.75
    },
    {
      "sensor_id": "plant1",
      "ts": "2026-02-25 03:00:00",
      "raw": 628.75,
      "moisture": 99.0,
      "vcc": null,
      "rssi": -64.75
    },
    {
      "sensor_id": "plant1",
      "ts": "2026-02-25 04:00:00",
      "raw": 628.25,
      "moisture": 98.75,
      "vcc": null,
      "rssi": -64.5
    },
    {
      "sensor_id": "plant1",
      "ts": "2026-02-25 05:00:00",
      "raw": 628.75,
      "moisture": 99.25,
      "vcc": null,
      "rssi": -64.75
    },
    {
      "sensor_id": "plant1",
      "ts": "2026-02-25 06:00:00",
      "raw": 628.0,
      "moisture": 98.5,
      "vcc": null,
      "rssi": -64.75
    },
    {
      "sensor_id": "plant1",
      "ts": "2026-02-25 07:00:00",
      "raw": 629.0,
      "moisture": 99.0,
      "vcc": null,
      "rssi": -64.5
    },
    {
      "sensor_id": "plant1",
      "ts": "2026-02-25 08:00:00",
      "raw": 629.75,
      "moisture": 99.25,
      "vcc": null,
      "rssi": -64.75
    },
    {
      "sensor_id": "plant1",
      "ts": "2026-02-25 09:00:00",
      "raw": 629.5,
      "moisture": 99.25,
      "vcc": null,
      "rssi": -65.0
    },
    {
      "sensor_id": "plant1",
      "ts": "2026-02-25 10:00:00",
      "raw": 630.5,
      "moisture": 99.75,
      "vcc": null,
      "rssi": -64.25
    },
    {
      "sensor_id": "plant1",
      "ts": "2026-02-25 11:00:00",
      "raw": 629.75,
      "moisture": 99.5,
      "vcc": null,
      "rssi": -64.75
    },
    {
      "sensor_id": "plant1",
      "ts": "2026-02-25 12:00:00",
      "raw": 627.25,
      "moisture": 98.5,
      "vcc": null,
      "rssi": -65.0
    },
    {
      "sensor_id": "plant1",
      "ts": "2026-02-25 13:00:00",
      "raw": 629.0,
      "moisture": 99.0,
      "vcc": null,
      "rssi": -65.0
    },
    {
      "sensor_id": "plant1",
      "ts": "2026-02-25 14:00:00",
      "raw": 628.0,
      "moisture": 99.0,
      "vcc": null,
      "rssi": -64.75
    },
    {
      "sensor_id": "plant1",
      "ts": "2026-02-25 15:00:00",
      "raw": 627.25,
      "moisture": 98.5,
      "vcc": null,
      "rssi": -64.75
    },
    {
      "sensor_id": "plant1",
      "ts": "2026-02-25 16:00:00",
      "raw": 628.5,
      "moisture": 99.0,
      "vcc": null,
      "rssi": -65.0
    },
    {
      "sensor_id": "plant1",
      "ts": "2026-02-25 17:00:00",
      "raw": 628.25,
      "moisture": 99.0,
      "vcc": null,
      "rssi": -64.25
    },
    {
      "sensor_id": "plant1",
      "ts": "2026-02-25 18:00:00",
      "raw": 627.0,
      "moisture": 98.25,
      "vcc": null,
      "rssi": -64.75
    },
    {
      "sensor_id": "plant1",
      "ts": "2026-02-25 19:00:00",
      "raw": 628.5,
      "moisture": 99.0,
      "vcc": null,
      "rssi": -64.25
    },
    {
      "sensor_id": "plant1",
      "ts": "2026-02-25 20:00:00",
      "raw": 626.75,
      "moisture": 98.0,
      "vcc": null,
      "rssi": -65.0
    },
    {
      "sensor_id": "plant1",
      "ts": "2026-02-25 21:00:00",
      "raw": 629.0,
      "moisture": 99.25,
      "vcc": null,
      "rssi": -65.0
    },
    {
      "sensor_id": "plant1",
      "ts": "2026-02-25 22:00:00",
      "raw": 628.75,
      "moisture": 99.0,
      "vcc": null,
      "rssi": -65.0
    },
    {
      "sensor_id": "plant1",
      "ts": "2026-02-25 23:00:00",
      "raw": 628.25,
      "moisture": 98.75,
      "vcc": null,
      "rssi": -65.0
    },
    {
      "sensor_id": "plant1",
      "ts": "2026-02-26 00:00:00",
      "raw": 628.5,
      "moisture": 99.0,
      "vcc": null,
      "rssi": -65.0
    },
    {
      "sensor_id": "plant1",
      "ts": "2026-02-26 01:00:00",
      "raw": 627.25,
      "moisture": 98.5,
      "vcc": null,
      "rssi": -65.0
    },
    {
      "sensor_id": "plant1",
      "ts": "2026-02-26 02:00:00",
      "raw": 629.25,
      "moisture": 99.5,
      "vcc": null,
      "rssi": -64.75
    },
    {
      "sensor_id": "plant1",
      "ts": "2026-02-26 03:00:00",
      "raw": 627.25,
      "moisture": 98.25,
      "vcc": null,
      "rssi": -65.0
    },
    {
      "sensor_id": "plant1",
      "ts": "2026-02-26 04:00:00",
      "raw": 626.0,
      "moisture": 97.75,
      "vcc": null,
      "rssi": -65.0
    },
    {
      "sensor_id": "plant1",
      "ts": "2026-02-26 05:00:00",
      "raw": 629.0,
      "moisture": 99.0,
      "vcc": null,
      "rssi": -65.0
    },
    {
      "sensor_id": "plant1",
      "ts": "2026-02-26 06:00:00",
      "raw": 628.75,
      "moisture": 99.25,
      "vcc": null,
      "rssi": -65.0
    },
    {
      "sensor_id": "plant1",
      "ts": "2026-02-26 07:00:00",
      "raw": 629.5,
      "moisture": 99.25,
      "vcc": null,
      "rssi": -65.0
    },
    {
      "sensor_id": "plant1",
      "ts": "2026-02-26 08:00:00",
      "raw": 628.5,
      "moisture": 99.0,
      "vcc": null,
      "rssi": -65.0
    },
    {
      "sensor_id": "plant1",
      "ts": "2026-02-26 09:00:00",
      "raw": 625.25,
      "moisture": 97.25,
      "vcc": null,
      "rssi": -65.0
    },
    {
      "sensor_id": "plant1",
      "ts": "2026-02-26 10:00:00",
      "raw": 625.75,
      "moisture": 97.75,
      "vcc": null,
      "rssi": -65.0
    },
    {
      "sensor_id": "plant1",
      "ts": "2026-02-26 11:00:00",
      "raw": 626.0,
      "moisture": 98.0,
      "vcc": null,
      "rssi": -65.25
    },
    {
      "sensor_id": "plant1",
      "ts": "2026-02-26 12:00:00",
      "raw": 626.25,
      "moisture": 97.75,
      "vcc": null,
      "rssi": -65.0
    },
    {
      "sensor_id": "plant1",
      "ts": "2026-02-26 13:00:00",
      "raw": 625.0,
      "moisture": 97.75,
      "vcc": null,
      "rssi": -65.5
    },
    {
      "sensor_id": "plant1",
      "ts": "2026-02-26 14:00:00",
      "raw": 627.75,
      "moisture": 98.75,
      "vcc": null,
      "rssi": -65.25
    },
    {
      "sensor_id": "plant1",
      "ts": "2026-02-26 15:00:00",
      "raw": 626.0,
      "moisture": 98.0,
      "vcc": null,
      "rssi": -65.5
    },
    {
      "sensor_id": "plant1",
      "ts": "2026-02-26 16:00:00",
      "raw": 626.75,
      "moisture": 98.25,
      "vcc": null,
      "rssi": -65.0
    },
    {
      "sensor_id": "plant1",
      "ts": "2026-02-26 17:00:00",
      "raw": 625.0,
      "moisture": 97.25,
      "vcc": null,
      "rssi": -65.0
    },
    {
      "sensor_id": "plant1",
      "ts": "2026-02-26 18:00:00",
      "raw": 626.5,
      "moisture": 98.0,
      "vcc": null,
      "rssi": -64.75
    },
    {
      "sensor_id": "plant1",
      "ts": "2026-02-26 19:00:00",
      "raw": 625.0,
      "moisture": 97.25,
      "vcc": null,
      "rssi": -65.5
    },
    {
      "sensor_id": "plant1",
      "ts": "2026-02-26 20:00:00",
      "raw": 626.75,
      "moisture": 98.25,
      "vcc": null,
      "rssi": -65.25
    },
    {
      "sensor_id": "plant1",
      "ts": "2026-02-26 21:00:00",
      "raw": 624.75,
      "moisture": 97.5,
      "vcc": null,
      "rssi": -65.0
    },
    {
      "sensor_id": "plant1",
      "ts": "2026-02-26 22:00:00",
      "raw": 625.5,
      "moisture": 97.75,
      "vcc": null,
      "rssi": -65.0
    },
    {
      "sensor_id": "plant1",
      "ts": "2026-02-26 23:00:00",
      "raw": 626.75,
      "moisture": 98.0,
      "vcc": null,
      "rssi": -65.0
    },
    {
      "sensor_id": "plant1",
      "ts": "2026-02-27 00:00:00",
      "raw": 625.25,
      "moisture": 97.5,
      "vcc": null,
      "rssi": -65.0
    },
    {
      "sensor_id": "plant1",
      "ts": "2026-02-27 01:00:00",
      "raw": 624.25,
      "moisture": 97.25,
      "vcc": null,
      "rssi": -65.25
    },
    {
      "sensor_id": "plant1",
      "ts": "2026-02-27 02:00:00",
      "raw": 625.25,
      "moisture": 97.5,
      "vcc": null,
      "rssi": -65.0
    },
    {
      "sensor_id": "plant1",
      "ts": "2026-02-27 03:00:00",
      "raw": 624.5,
      "moisture": 97.25,
      "vcc": null,
      "rssi": -65.0
    },
    {
      "sensor_id": "plant1",
      "ts": "2026-02-27 04:00:00",
      "raw": 624.25,
      "moisture": 97.25,
      "vcc": null,
      "rssi": -65.0
    },
    {
      "sensor_id": "plant1",
      "ts": "2026-02-27 05:00:00",
      "raw": 627.25,
      "moisture": 98.25,
      "vcc": null,
      "rssi": -65.0
    },
    {
      "sensor_id": "plant1",
      "ts": "2026-02-27 06:00:00",
      "raw": 626.5,
      "moisture": 98.0,
      "vcc": null,
      "rssi": -65.0
    },
    {
      "sensor_id": "plant1",
      "ts": "2026-02-27 07:00:00",
      "raw": 626.5,
      "moisture": 98.0,
      "vcc": null,
      "rssi": -65.0
    },
    {
      "sensor_id": "plant1",
      "ts": "2026-02-27 08:00:00",
      "raw": 624.5,
      "moisture": 97.0,
      "vcc": null,
      "rssi": -65.0
    },
    {
      "sensor_id": "plant1",
      "ts": "2026-02-27 09:00:00",
      "raw": 623.0,
      "moisture": 96.75,
      "vcc": null,
      "rssi": -65.25
    },
    {
      "sensor_id": "plant1",
      "ts": "2026-02-27 10:00:00",
      "raw": 621.75,
      "moisture": 96.25,
      "vcc": null,
      "rssi": -65.0
    },
    {
      "sensor_id": "plant1",
      "ts": "2026-02-27 11:00:00",
      "raw": 622.75,
      "moisture": 96.5,
      "vcc": null,
      "rssi": -65.75
    },
    {
      "sensor_id": "plant1",
      "ts": "2026-02-27 12:00:00",
      "raw": 623.0,
      "moisture": 96.5,
      "vcc": null,
      "rssi": -65.25
    },
    {
      "sensor_id": "plant1",
      "ts": "2026-02-27 13:00:00",
      "raw": 621.5,
      "moisture": 96.0,
      "vcc": null,
      "rssi": -65.0
    },
    {
      "sensor_id": "plant1",
      "ts": "2026-02-27 14:00:00",
      "raw": 622.5,
      "moisture": 96.5,
      "vcc": null,
      "rssi": -65.75
    },
    {
      "sensor_id": "plant1",
      "ts": "2026-02-27 15:00:00",
      "raw": 624.5,
      "moisture": 97.25,
      "vcc": null,
      "rssi": -65.5
    },
    {
      "sensor_id": "plant1",
      "ts": "2026-02-27 16:00:00",
      "raw": 622.0,
      "moisture": 96.5,
      "vcc": null,
      "rssi": -65.0
    },
    {
      "sensor_id": "plant1",
      "ts": "2026-02-27 17:00:00",
      "raw": 623.25,
      "moisture": 96.75,
      "vcc": null,
      "rssi": -65.0
    },
    {
      "sensor_id": "plant1",
      "ts": "2026-02-27 18:00:00",
      "raw": 623.5,
      "moisture": 97.0,
      "vcc": null,
      "rssi": -65.25
    },
    {
      "sensor_id": "plant1",
      "ts": "2026-02-27 19:00:00",
      "raw": 624.75,
      "moisture": 97.5,
      "vcc": null,
      "rssi": -65.0
    },
    {
      "sensor_id": "plant1",
      "ts": "2026-02-27 20:00:00",
      "raw": 625.0,
      "moisture": 97.5,
      "vcc": null,
      "rssi": -65.0
    },
    {
      "sensor_id": "plant1",
      "ts": "2026-02-27 21:00:00",
      "raw": 624.0,
      "moisture": 97.0,
      "vcc": null,
      "rssi": -65.5
    },
    {
      "sensor_id": "plant1",
      "ts": "2026-02-27 22:00:00",
      "raw": 623.5,
      "moisture": 96.5,
      "vcc": null,
      "rssi": -65.5
    },
    {
      "sensor_id": "plant1",
      "ts": "2026-02-27 23:00:00",
      "raw": 625.25,
      "moisture": 97.5,
      "vcc": null,
      "rssi": -65.25
    },
    {
      "sensor_id": "plant1",
      "ts": "2026-02-28 00:00:00",
      "raw": 623.5,
      "moisture": 97.0,
      "vcc": null,
      "rssi": -65.0
    },
    {
      "sensor_id": "plant1",
      "ts": "2026-02-28 01:00:00",
      "raw": 624.75,
      "moisture": 97.0,
      "vcc": null,
      "rssi": -65.5
    },
    {
      "sensor_id": "plant1",
      "ts": "2026-02-28 02:00:00",
      "raw": 624.0,
      "moisture": 97.0,
      "vcc": null,
      "rssi": -65.25
    },
    {
      "sensor_id": "plant1",
      "ts": "2026-02-28 03:00:00",
      "raw": 623.5,
      "moisture": 96.75,
      "vcc": null,
      "rssi": -65.5
    },
    {
      "sensor_id": "plant1",
      "ts": "2026-02-28 04:00:00",
      "raw": 625.25,
      "moisture": 97.5,
      "vcc": null,
      "rssi": -65.5
    },
    {
      "sensor_id": "plant1",
      "ts": "2026-02-28 05:00:00",
      "raw": 624.75,
      "moisture": 97.0,
      "vcc": null,
      "rssi": -65.25
    },
    {
      "sensor_id": "plant1",
      "ts": "2026-02-28 06:00:00",
      "raw": 624.75,
      "moisture": 97.25,
      "vcc": null,
      "rssi": -65.0
    },
    {
      "sensor_id": "plant1",
      "ts": "2026-02-28 07:00:00",
      "raw": 626.0,
      "moisture": 97.75,
      "vcc": null,
      "rssi": -65.25
    },
    {
      "sensor_id": "plant1",
      "ts": "2026-02-28 08:00:00",
      "raw": 624.0,
      "moisture": 97.25,
      "vcc": null,
      "rssi": -65.25
    },
    {
      "sensor_id": "plant1",
      "ts": "2026-02-28 09:00:00",
      "raw": 623.25,
      "moisture": 96.75,
      "vcc": null,
      "rssi": -65.0
    },
    {
      "sensor_id": "plant1",
      "ts": "2026-02-28 10:00:00",
      "raw": 626.25,
      "moisture": 98.0,
      "vcc": null,
      "rssi": -64.75
    },
    {
      "sensor_id": "plant1",
      "ts": "2026-02-28 11:00:00",
      "raw": 623.0,
      "moisture": 96.75,
      "vcc": null,
      "rssi": -65.0
    },
    {
      "sensor_id": "plant1",
      "ts": "2026-02-28 12:00:00",
      "raw": 625.25,
      "moisture": 97.25,
      "vcc": null,
      "rssi": -64.75
    },
    {
      "sensor_id": "plant1",
      "ts": "2026-02-28 13:00:00",
      "raw": 625.25,
      "moisture": 97.5,
      "vcc": null,
      "rssi": -65.0
    },
    {
      "sensor_id": "plant1",
      "ts": "2026-02-28 14:00:00",
      "raw": 626.0,
      "moisture": 97.75,
      "vcc": null,
      "rssi": -64.75
    },
    {
      "sensor_id": "plant1",
      "ts": "2026-02-28 15:00:00",
      "raw": 626.5,
      "moisture": 98.0,
      "vcc": null,
      "rssi": -64.5
    },
    {
      "sensor_id": "plant1",
      "ts": "2026-02-28 16:00:00",
      "raw": 625.0,
      "moisture": 97.5,
      "vcc": null,
      "rssi": -64.5
    },
    {
      "sensor_id": "plant1",
      "ts": "2026-02-28 17:00:00",
      "raw": 624.75,
      "moisture": 97.25,
      "vcc": null,
      "rssi": -64.0
    },
    {
      "sensor_id": "plant1",
      "ts": "2026-02-28 18:00:00",
      "raw": 624.5,
      "moisture": 97.0,
      "vcc": null,
      "rssi": -64.5
    },
    {
      "sensor_id": "plant1",
      "ts": "2026-02-28 19:00:00",
      "raw": 625.25,
      "moisture": 97.5,
      "vcc": null,
      "rssi": -64.25
    },
    {
      "sensor_id": "plant1",
      "ts": "2026-02-28 20:00:00",
      "raw": 626.25,
      "moisture": 98.0,
      "vcc": null,
      "rssi": -64.0
    },
    {
      "sensor_id": "plant1",
      "ts": "2026-02-28 21:00:00",
      "raw": 628.25,
      "moisture": 99.0,
      "vcc": null,
      "rssi": -65.0
    },
    {
      "sensor_id": "plant1",
      "ts": "2026-02-28 22:00:00",
      "raw": 626.75,
      "moisture": 98.0,
      "vcc": null,
      "rssi": -64.25
    },
    {
      "sensor_id": "plant1",
      "ts": "2026-02-28 23:00:00",
      "raw": 629.5,
      "moisture": 99.0,
      "vcc": null,
      "rssi": -64.0
    },
    {
      "sensor_id": "plant1",
      "ts": "2026-03-01 00:00:00",
      "raw": 625.5,
      "moisture": 97.5,
      "vcc": null,
      "rssi": -64.0
    },
    {
      "sensor_id": "plant1",
      "ts": "2026-03-01 01:00:00",
      "raw": 625.5,
      "moisture": 97.5,
      "vcc": null,
      "rssi": -64.0
    },
    {
      "sensor_id": "plant1",
      "ts": "2026-03-01 02:00:00",
      "raw": 625.25,
      "moisture": 97.5,
      "vcc": null,
      "rssi": -64.5
    },
    {
      "sensor_id": "plant1",
      "ts": "2026-03-01 03:00:00",
      "raw": 625.5,
      "moisture": 97.75,
      "vcc": null,
      "rssi": -64.0
    },
    {
      "sensor_id": "plant1",
      "ts": "2026-03-01 04:00:00",
      "raw": 624.5,
      "moisture": 97.25,
      "vcc": null,
      "rssi": -64.0
    },
    {
      "sensor_id": "plant1",
      "ts": "2026-03-01 05:00:00",
      "raw": 626.25,
      "moisture": 97.75,
      "vcc": null,
      "rssi": -64.25
    },
    {
      "sensor_id": "plant1",
      "ts": "2026-03-01 06:00:00",
      "raw": 627.0,
      "moisture": 98.25,
      "vcc": null,
      "rssi": -64.5
    },
    {
      "sensor_id": "plant1",
      "ts": "2026-03-01 07:00:00",
      "raw": 626.5,
      "moisture": 98.0,
      "vcc": null,
      "rssi": -64.5
    },
    {
      "sensor_id": "plant1",
      "ts": "2026-03-01 08:00:00",
      "raw": 626.75,
      "moisture": 98.25,
      "vcc": null,
      "rssi": -64.5
    },
    {
      "sensor_id": "plant1",
      "ts": "2026-03-01 09:00:00",
      "raw": 626.5,
      "moisture": 98.0,
      "vcc": null,
      "rssi": -64.5
    },
    {
      "sensor_id": "plant1",
      "ts": "2026-03-01 10:00:00",
      "raw": 629.75,
      "moisture": 99.25,
      "vcc": null,
      "rssi": -64.0
    },
    {
      "sensor_id": "plant1",
      "ts": "2026-03-01 11:00:00",
      "raw": 632.0,
      "moisture": 100.0,
      "vcc": null,
      "rssi": -65.75
    },
    {
      "sensor_id": "plant1",
      "ts": "2026-03-01 12:00:00",
      "raw": 628.5,
      "moisture": 99.0,
      "vcc": null,
      "rssi": -63.5
    },
    {
      "sensor_id": "plant1",
      "ts": "2026-03-01 13:00:00",
      "raw": 631.25,
      "moisture": 100.0,
      "vcc": null,
      "rssi": -63.0
    },
    {
      "sensor_id": "plant1",
      "ts": "2026-03-01 14:00:00",
      "raw": 628.5,
      "moisture": 98.75,
      "vcc": null,
      "rssi": -64.25
    },
    {
      "sensor_id": "plant1",
      "ts": "2026-03-01 15:00:00",
      "raw": 625.25,
      "moisture": 97.25,
      "vcc": null,
      "rssi": -64.0
    },
    {
      "sensor_id": "plant1",
      "ts": "2026-03-01 16:00:00",
      "raw": 629.5,
      "moisture": 99.5,
      "vcc": null,
      "rssi": -64.75
    },
    {
      "sensor_id": "plant1",
      "ts": "2026-03-01 17:00:00",
      "raw": 625.0,
      "moisture": 97.25,
      "vcc": null,
      "rssi": -63.75
    },
    {
      "sensor_id": "plant1",
      "ts": "2026-03-01 18:00:00",
      "raw": 626.0,
      "moisture": 97.75,
      "vcc": null,
      "rssi": -64.25
    },
    {
      "sensor_id": "plant1",
      "ts": "2026-03-01 19:00:00",
      "raw": 625.25,
      "moisture": 97.75,
      "vcc": null,
      "rssi": -63.75
    },
    {
      "sensor_id": "plant1",
      "ts": "2026-03-01 20:00:00",
      "raw": 625.0,
      "moisture": 97.25,
      "vcc": null,
      "rssi": -63.5
    },
    {
      "sensor_id": "plant1",
      "ts": "2026-03-01 21:00:00",
      "raw": 625.0,
      "moisture": 97.5,
      "vcc": null,
      "rssi": -64.0
    },
    {
      "sensor_id": "plant1",
      "ts": "2026-03-01 22:00:00",
      "raw": 625.5,
      "moisture": 97.75,
      "vcc": null,
      "rssi": -64.25
    },
    {
      "sensor_id": "plant1",
      "ts": "2026-03-01 23:00:00",
      "raw": 626.25,
      "moisture": 97.75,
      "vcc": null,
      "rssi": -63.25
    },
    {
      "sensor_id": "plant1",
      "ts": "2026-03-02 00:00:00",
      "raw": 624.25,
      "moisture": 97.25,
      "vcc": null,
      "rssi": -63.5
    },
    {
      "sensor_id": "plant1",
      "ts": "2026-03-02 01:00:00",
      "raw": 625.25,
      "moisture": 97.5,
      "vcc": null,
      "rssi": -63.75
    },
    {
      "sensor_id": "plant1",
      "ts": "2026-03-02 02:00:00",
      "raw": 625.25,
      "moisture": 97.5,
      "vcc": null,
      "rssi": -63.25
    },
    {
      "sensor_id": "plant1",
      "ts": "2026-03-02 03:00:00",
      "raw": 624.25,
      "moisture": 97.25,
      "vcc": null,
      "rssi": -63.5
    },
    {
      "sensor_id": "plant1",
      "ts": "2026-03-02 04:00:00",
      "raw": 624.5,
      "moisture": 97.0,
      "vcc": null,
      "rssi": -64.0
    },
    {
      "sensor_id": "plant1",
      "ts": "2026-03-02 05:00:00",
      "raw": 626.0,
      "moisture": 97.75,
      "vcc": null,
      "rssi": -63.25
    },
    {
      "sensor_id": "plant1",
      "ts": "2026-03-02 06:00:00",
      "raw": 624.75,
      "moisture": 97.5,
      "vcc": null,
      "rssi": -64.25
    },
    {
      "sensor_id": "plant1",
      "ts": "2026-03-02 07:00:00",
      "raw": 626.25,
      "moisture": 98.0,
      "vcc": null,
      "rssi": -64.25
    },
    {
      "sensor_id": "plant1",
      "ts": "2026-03-02 08:00:00",
      "raw": 630.75,
      "moisture": 99.75,
      "vcc": null,
      "rssi": -63.75
    },
    {
      "sensor_id": "plant1",
      "ts": "2026-03-02 09:00:00",
      "raw": 625.0,
      "moisture": 97.5,
      "vcc": null,
      "rssi": -64.0
    },
    {
      "sensor_id": "plant1",
      "ts": "2026-03-02 10:00:00",
      "raw": 622.0,
      "moisture": 96.25,
      "vcc": null,
      "rssi": -63.75
    },
    {
      "sensor_id": "plant1",
      "ts": "2026-03-02 11:00:00",
      "raw": 622.0,
      "moisture": 96.0,
      "vcc": null,
      "rssi": -64.5
    },
    {
      "sensor_id": "plant1",
      "ts": "2026-03-02 12:00:00",
      "raw": 622.5,
      "moisture": 96.5,
      "vcc": null,
      "rssi": -64.25
    },
    {
      "sensor_id": "plant1",
      "ts": "2026-03-02 13:00:00",
      "raw": 621.25,
      "moisture": 96.25,
      "vcc": null,
      "rssi": -64.25
    },
    {
      "sensor_id": "plant1",
      "ts": "2026-03-02 14:00:00",
      "raw": 623.25,
      "moisture": 96.5,
      "vcc": null,
      "rssi": -64.5
    },
    {
      "sensor_id": "plant1",
      "ts": "2026-03-02 15:00:00",
      "raw": 624.0,
      "moisture": 97.0,
      "vcc": null,
      "rssi": -64.5
    },
    {
      "sensor_id": "plant1",
      "ts": "2026-03-02 16:00:00",
      "raw": 623.0,
      "moisture": 96.5,
      "vcc": null,
      "rssi": -64.0
    },
    {
      "sensor_id": "plant1",
      "ts": "2026-03-02 17:00:00",
      "raw": 624.25,
      "moisture": 97.0,
      "vcc": null,
      "rssi": -64.25
    },
    {
      "sensor_id": "plant1",
      "ts": "2026-03-02 18:00:00",
      "raw": 624.0,
      "moisture": 97.0,
      "vcc": null,
      "rssi": -66.25
    },
    {
      "sensor_id": "plant1",
      "ts": "2026-03-02 19:00:00",
      "raw": 624.25,
      "moisture": 97.0,
      "vcc": null,
      "rssi": -66.0
    },
    {
      "sensor_id": "plant1",
      "ts": "2026-03-02 20:00:00",
      "raw": 627.0,
      "moisture": 98.25,
      "vcc": null,
      "rssi": -65.75
    },
    {
      "sensor_id": "plant1",
      "ts": "2026-03-02 21:00:00",
      "raw": 626.0,
      "moisture": 97.75,
      "vcc": null,
      "rssi": -65.0
    },
    {
      "sensor_id": "plant1",
      "ts": "2026-03-02 22:00:00",
      "raw": 627.5,
      "moisture": 98.5,
      "vcc": null,
      "rssi": -65.25
    },
    {
      "sensor_id": "plant1",
      "ts": "2026-03-02 23:00:00",
      "raw": 627.0,
      "moisture": 98.25,
      "vcc": null,
      "rssi": -65.25
    },
    {
      "sensor_id": "plant1",
      "ts": "2026-03-03 00:00:00",
      "raw": 628.25,
      "moisture": 98.75,
      "vcc": null,
      "rssi": -65.75
    },
    {
      "sensor_id": "plant1",
      "ts": "2026-03-03 01:00:00",
      "raw": 627.0,
      "moisture": 98.0,
      "vcc": null,
      "rssi": -65.5
    },
    {
      "sensor_id": "plant1",
      "ts": "2026-03-03 02:00:00",
      "raw": 627.25,
      "moisture": 98.5,
      "vcc": null,
      "rssi": -65.75
    },
    {
      "sensor_id": "plant1",
      "ts": "2026-03-03 03:00:00",
      "raw": 626.25,
      "moisture": 98.0,
      "vcc": null,
      "rssi": -65.25
    },
    {
      "sensor_id": "plant1",
      "ts": "2026-03-03 04:00:00",
      "raw": 628.25,
      "moisture": 98.75,
      "vcc": null,
      "rssi": -65.5
    },
    {
      "sensor_id": "plant1",
      "ts": "2026-03-03 05:00:00",
      "raw": 628.0,
      "moisture": 98.75,
      "vcc": null,
      "rssi": -65.75
    },
    {
      "sensor_id": "plant1",
      "ts": "2026-03-03 06:00:00",
      "raw": 630.25,
      "moisture": 99.5,
      "vcc": null,
      "rssi": -66.5
    },
    {
      "sensor_id": "plant1",
      "ts": "2026-03-03 07:00:00",
      "raw": 627.0,
      "moisture": 98.25,
      "vcc": null,
      "rssi": -66.75
    },
    {
      "sensor_id": "plant1",
      "ts": "2026-03-03 08:00:00",
      "raw": 625.5,
      "moisture": 97.5,
      "vcc": null,
      "rssi": -66.75
    },
    {
      "sensor_id": "plant1",
      "ts": "2026-03-03 09:00:00",
      "raw": 620.25,
      "moisture": 95.5,
      "vcc": null,
      "rssi": -67.0
    },
    {
      "sensor_id": "plant1",
      "ts": "2026-03-03 10:00:00",
      "raw": 619.0,
      "moisture": 95.0,
      "vcc": null,
      "rssi": -67.0
    },
    {
      "sensor_id": "plant1",
      "ts": "2026-03-03 11:00:00",
      "raw": 620.75,
      "moisture": 95.75,
      "vcc": null,
      "rssi": -66.75
    },
    {
      "sensor_id": "plant1",
      "ts": "2026-03-03 12:00:00",
      "raw": 621.25,
      "moisture": 96.0,
      "vcc": null,
      "rssi": -66.0
    },
    {
      "sensor_id": "plant1",
      "ts": "2026-03-03 13:00:00",
      "raw": 623.25,
      "moisture": 96.75,
      "vcc": null,
      "rssi": -66.0
    },
    {
      "sensor_id": "plant1",
      "ts": "2026-03-03 14:00:00",
      "raw": 620.75,
      "moisture": 95.5,
      "vcc": null,
      "rssi": -66.75
    },
    {
      "sensor_id": "plant1",
      "ts": "2026-03-03 15:00:00",
      "raw": 621.25,
      "moisture": 95.75,
      "vcc": null,
      "rssi": -66.25
    },
    {
      "sensor_id": "plant1",
      "ts": "2026-03-03 16:00:00",
      "raw": 621.25,
      "moisture": 95.75,
      "vcc": null,
      "rssi": -66.5
    },
    {
      "sensor_id": "plant1",
      "ts": "2026-03-03 17:00:00",
      "raw": 621.75,
      "moisture": 96.25,
      "vcc": null,
      "rssi": -66.0
    },
    {
      "sensor_id": "plant1",
      "ts": "2026-03-03 18:00:00",
      "raw": 621.75,
      "moisture": 96.0,
      "vcc": null,
      "rssi": -66.0
    },
    {
      "sensor_id": "plant1",
      "ts": "2026-03-03 19:00:00",
      "raw": 623.0,
      "moisture": 96.75,
      "vcc": null,
      "rssi": -66.0
    },
    {
      "sensor_id": "plant1",
      "ts": "2026-03-03 20:00:00",
      "raw": 624.25,
      "moisture": 97.0,
      "vcc": null,
      "rssi": -66.0
    },
    {
      "sensor_id": "plant1",
      "ts": "2026-03-03 21:00:00",
      "raw": 623.0,
      "moisture": 96.75,
      "vcc": null,
      "rssi": -66.0
    },
    {
      "sensor_id": "plant1",
      "ts": "2026-03-03 22:00:00",
      "raw": 624.0,
      "moisture": 97.0,
      "vcc": null,
      "rssi": -66.75
    },
    {
      "sensor_id": "plant1",
      "ts": "2026-03-03 23:00:00",
      "raw": 624.25,
      "moisture": 97.25,
      "vcc": null,
      "rssi": -66.5
    },
    {
      "sensor_id": "plant1",
      "ts": "2026-03-04 00:00:00",
      "raw": 623.25,
      "moisture": 96.75,
      "vcc": null,
      "rssi": -67.0
    },
    {
      "sensor_id": "plant1",
      "ts": "2026-03-04 01:00:00",
      "raw": 626.0,
      "moisture": 97.75,
      "vcc": null,
      "rssi": -67.0
    },
    {
      "sensor_id": "plant1",
      "ts": "2026-03-04 02:00:00",
      "raw": 625.75,
      "moisture": 98.0,
      "vcc": null,
      "rssi": -67.0
    },
    {
      "sensor_id": "plant1",
      "ts": "2026-03-04 03:00:00",
      "raw": 625.75,
      "moisture": 97.5,
      "vcc": null,
      "rssi": -66.75
    },
    {
      "sensor_id": "plant1",
      "ts": "2026-03-04 04:00:00",
      "raw": 626.25,
      "moisture": 97.75,
      "vcc": null,
      "rssi": -66.75
    },
    {
      "sensor_id": "plant1",
      "ts": "2026-03-04 05:00:00",
      "raw": 624.5,
      "moisture": 97.0,
      "vcc": null,
      "rssi": -67.0
    },
    {
      "sensor_id": "plant1",
      "ts": "2026-03-04 06:00:00",
      "raw": 625.25,
      "moisture": 97.5,
      "vcc": null,
      "rssi": -64.25
    },
    {
      "sensor_id": "plant1",
      "ts": "2026-03-04 07:00:00",
      "raw": 623.75,
      "moisture": 97.0,
      "vcc": null,
      "rssi": -64.0
    },
    {
      "sensor_id": "plant1",
      "ts": "2026-03-04 08:00:00",
      "raw": 621.5,
      "moisture": 96.0,
      "vcc": null,
      "rssi": -64.25
    },
    {
      "sensor_id": "plant1",
      "ts": "2026-03-04 09:00:00",
      "raw": 619.0,
      "moisture": 95.0,
      "vcc": null,
      "rssi": -64.0
    },
    {
      "sensor_id": "plant1",
      "ts": "2026-03-04 10:00:00",
      "raw": 619.75,
      "moisture": 95.25,
      "vcc": null,
      "rssi": -64.25
    },
    {
      "sensor_id": "plant1",
      "ts": "2026-03-04 11:00:00",
      "raw": 618.5,
      "moisture": 95.0,
      "vcc": null,
      "rssi": -64.25
    },
    {
      "sensor_id": "plant1",
      "ts": "2026-03-04 12:00:00",
      "raw": 618.0,
      "moisture": 94.5,
      "vcc": null,
      "rssi": -64.5
    },
    {
      "sensor_id": "plant1",
      "ts": "2026-03-04 13:00:00",
      "raw": 618.5,
      "moisture": 94.75,
      "vcc": null,
      "rssi": -64.0
    },
    {
      "sensor_id": "plant1",
      "ts": "2026-03-04 14:00:00",
      "raw": 619.5,
      "moisture": 95.0,
      "vcc": null,
      "rssi": -64.0
    },
    {
      "sensor_id": "plant1",
      "ts": "2026-03-04 15:00:00",
      "raw": 618.75,
      "moisture": 95.25,
      "vcc": null,
      "rssi": -64.0
    },
    {
      "sensor_id": "plant1",
      "ts": "2026-03-04 16:00:00",
      "raw": 621.0,
      "moisture": 95.5,
      "vcc": null,
      "rssi": -64.0
    },
    {
      "sensor_id": "plant1",
      "ts": "2026-03-04 17:00:00",
      "raw": 622.25,
      "moisture": 96.5,
      "vcc": null,
      "rssi": -63.75
    },
    {
      "sensor_id": "plant1",
      "ts": "2026-03-04 18:00:00",
      "raw": 619.75,
      "moisture": 95.25,
      "vcc": null,
      "rssi": -64.0
    },
    {
      "sensor_id": "plant1",
      "ts": "2026-03-04 19:00:00",
      "raw": 623.75,
      "moisture": 97.0,
      "vcc": null,
      "rssi": -63.75
    },
    {
      "sensor_id": "plant1",
      "ts": "2026-03-04 20:00:00",
      "raw": 623.0,
      "moisture": 96.5,
      "vcc": null,
      "rssi": -64.0
    },
    {
      "sensor_id": "plant1",
      "ts": "2026-03-04 21:00:00",
      "raw": 624.25,
      "moisture": 97.0,
      "vcc": null,
      "rssi": -64.0
    },
    {
      "sensor_id": "plant1",
      "ts": "2026-03-04 22:00:00",
      "raw": 625.75,
      "moisture": 97.75,
      "vcc": null,
      "rssi": -64.0
    },
    {
      "sensor_id": "plant1",
      "ts": "2026-03-04 23:00:00",
      "raw": 624.25,
      "moisture": 97.25,
      "vcc": null,
      "rssi": -63.75
    },
    {
      "sensor_id": "plant1",
      "ts": "2026-03-05 00:00:00",
      "raw": 624.0,
      "moisture": 97.0,
      "vcc": null,
      "rssi": -64.0
    },
    {
      "sensor_id": "plant1",
      "ts": "2026-03-05 01:00:00",
      "raw": 626.0,
      "moisture": 97.75,
      "vcc": null,
      "rssi": -64.0
    },
    {
      "sensor_id": "plant1",
      "ts": "2026-03-05 02:00:00",
      "raw": 624.5,
      "moisture": 97.0,
      "vcc": null,
      "rssi": -64.0
    },
    {
      "sensor_id": "plant1",
      "ts": "2026-03-05 03:00:00",
      "raw": 624.25,
      "moisture": 97.0,
      "vcc": null,
      "rssi": -63.75
    },
    {
      "sensor_id": "plant1",
      "ts": "2026-03-05 04:00:00",
      "raw": 626.5,
      "moisture": 98.0,
      "vcc": null,
      "rssi": -64.0
    },
    {
      "sensor_id": "plant1",
      "ts": "2026-03-05 05:00:00",
      "raw": 625.0,
      "moisture": 97.5,
      "vcc": null,
      "rssi": -64.0
    },
    {
      "sensor_id": "plant1",
      "ts": "2026-03-05 06:00:00",
      "raw": 625.0,
      "moisture": 97.5,
      "vcc": null,
      "rssi": -64.0
    },
    {
      "sensor_id": "plant1",
      "ts": "2026-03-05 07:00:00",
      "raw": 623.0,
      "moisture": 96.75,
      "vcc": null,
      "rssi": -64.0
    },
    {
      "sensor_id": "plant1",
      "ts": "2026-03-05 08:00:00",
      "raw": 622.0,
      "moisture": 96.25,
      "vcc": null,
      "rssi": -64.25
    },
    {
      "sensor_id": "plant1",
      "ts": "2026-03-05 09:00:00",
      "raw": 620.0,
      "moisture": 95.25,
      "vcc": null,
      "rssi": -64.25
    },
    {
      "sensor_id": "plant1",
      "ts": "2026-03-05 10:00:00",
      "raw": 619.0,
      "moisture": 95.0,
      "vcc": null,
      "rssi": -64.0
    },
    {
      "sensor_id": "plant1",
      "ts": "2026-03-05 11:00:00",
      "raw": 618.25,
      "moisture": 94.75,
      "vcc": null,
      "rssi": -64.0
    },
    {
      "sensor_id": "plant1",
      "ts": "2026-03-05 12:00:00",
      "raw": 617.25,
      "moisture": 94.25,
      "vcc": null,
      "rssi": -64.0
    },
    {
      "sensor_id": "plant1",
      "ts": "2026-03-05 13:00:00",
      "raw": 617.5,
      "moisture": 94.5,
      "vcc": null,
      "rssi": -64.0
    },
    {
      "sensor_id": "plant1",
      "ts": "2026-03-05 14:00:00",
      "raw": 620.25,
      "moisture": 95.5,
      "vcc": null,
      "rssi": -63.75
    },
    {
      "sensor_id": "plant1",
      "ts": "2026-03-05 15:00:00",
      "raw": 617.75,
      "moisture": 94.5,
      "vcc": null,
      "rssi": -64.0
    },
    {
      "sensor_id": "plant1",
      "ts": "2026-03-05 16:00:00",
      "raw": 619.75,
      "moisture": 95.25,
      "vcc": null,
      "rssi": -64.0
    },
    {
      "sensor_id": "plant1",
      "ts": "2026-03-05 17:00:00",
      "raw": 621.0,
      "moisture": 95.75,
      "vcc": null,
      "rssi": -64.0
    },
    {
      "sensor_id": "plant1",
      "ts": "2026-03-05 18:00:00",
      "raw": 621.75,
      "moisture": 96.25,
      "vcc": null,
      "rssi": -64.0
    },
    {
      "sensor_id": "plant1",
      "ts": "2026-03-05 19:00:00",
      "raw": 623.25,
      "moisture": 96.75,
      "vcc": null,
      "rssi": -65.75
    },
    {
      "sensor_id": "plant1",
      "ts": "2026-03-05 20:00:00",
      "raw": 622.75,
      "moisture": 96.75,
      "vcc": null,
      "rssi": -64.0
    },
    {
      "sensor_id": "plant1",
      "ts": "2026-03-05 21:00:00",
      "raw": 622.0,
      "moisture": 96.25,
      "vcc": null,
      "rssi": -64.0
    },
    {
      "sensor_id": "plant1",
      "ts": "2026-03-05 22:00:00",
      "raw": 623.75,
      "moisture": 97.0,
      "vcc": null,
      "rssi": -64.0
    },
    {
      "sensor_id": "plant1",
      "ts": "2026-03-05 23:00:00",
      "raw": 624.75,
      "moisture": 97.5,
      "vcc": null,
      "rssi": -64.0
    },
    {
      "sensor_id": "plant1",
      "ts": "2026-03-06 00:00:00",
      "raw": 622.75,
      "moisture": 96.25,
      "vcc": null,
      "rssi": -64.0
    },
    {
      "sensor_id": "plant1",
      "ts": "2026-03-06 01:00:00",
      "raw": 624.0,
      "moisture": 97.0,
      "vcc": null,
      "rssi": -64.0
    },
    {
      "sensor_id": "plant1",
      "ts": "2026-03-06 02:00:00",
      "raw": 624.0,
      "moisture": 97.25,
      "vcc": null,
      "rssi": -64.0
    },
    {
      "sensor_id": "plant1",
      "ts": "2026-03-06 03:00:00",
      "raw": 624.75,
      "moisture": 97.25,
      "vcc": null,
      "rssi": -64.0
    },
    {
      "sensor_id": "plant1",
      "ts": "2026-03-06 04:00:00",
      "raw": 625.25,
      "moisture": 97.5,
      "vcc": null,
      "rssi": -64.5
    },
    {
      "sensor_id": "plant1",
      "ts": "2026-03-06 05:00:00",
      "raw": 626.25,
      "moisture": 98.0,
      "vcc": null,
      "rssi": -64.0
    },
    {
      "sensor_id": "plant1",
      "ts": "2026-03-06 06:00:00",
      "raw": 623.25,
      "moisture": 97.0,
      "vcc": null,
      "rssi": -64.0
    },
    {
      "sensor_id": "plant1",
      "ts": "2026-03-06 07:00:00",
      "raw": 625.0,
      "moisture": 97.5,
      "vcc": null,
      "rssi": -64.5
    },
    {
      "sensor_id": "plant1",
      "ts": "2026-03-06 08:00:00",
      "raw": 622.5,
      "moisture": 96.5,
      "vcc": null,
      "rssi": -64.0
    },
    {
      "sensor_id": "plant1",
      "ts": "2026-03-06 09:00:00",
      "raw": 619.75,
      "moisture": 95.25,
      "vcc": null,
      "rssi": -64.5
    },
    {
      "sensor_id": "plant1",
      "ts": "2026-03-06 10:00:00",
      "raw": 619.25,
      "moisture": 95.0,
      "vcc": null,
      "rssi": -64.0
    },
    {
      "sensor_id": "plant1",
      "ts": "2026-03-06 11:00:00",
      "raw": 618.75,
      "moisture": 94.75,
      "vcc": null,
      "rssi": -64.0
    },
    {
      "sensor_id": "plant1",
      "ts": "2026-03-06 12:00:00",
      "raw": 620.0,
      "moisture": 95.5,
      "vcc": null,
      "rssi": -64.0
    },
    {
      "sensor_id": "plant1",
      "ts": "2026-03-06 13:00:00",
      "raw": 619.75,
      "moisture": 95.25,
      "vcc": null,
      "rssi": -64.0
    },
    {
      "sensor_id": "plant1",
      "ts": "2026-03-06 14:00:00",
      "raw": 620.0,
      "moisture": 95.25,
      "vcc": null,
      "rssi": -64.0
    },
    {
      "sensor_id": "plant1",
      "ts": "2026-03-06 15:00:00",
      "raw": 618.25,
      "moisture": 94.75,
      "vcc": null,
      "rssi": -63.5
    },
    {
      "sensor_id": "plant1",
      "ts": "2026-03-06 16:00:00",
      "raw": 618.5,
      "moisture": 94.75,
      "vcc": null,
      "rssi": -64.25
    },
    {
      "sensor_id": "plant1",
      "ts": "2026-03-06 17:00:00",
      "raw": 620.0,
      "moisture": 95.25,
      "vcc": null,
      "rssi": -64.5
    },
    {
      "sensor_id": "plant1",
      "ts": "2026-03-06 18:00:00",
      "raw": 621.25,
      "moisture": 96.0,
      "vcc": null,
      "rssi": -64.0
    },
    {
      "sensor_id": "plant1",
      "ts": "2026-03-06 19:00:00",
      "raw": 620.75,
      "moisture": 95.5,
      "vcc": null,
      "rssi": -64.0
    },
    {
      "sensor_id": "plant1",
      "ts": "2026-03-06 20:00:00",
      "raw": 623.0,
      "moisture": 96.75,
      "vcc": null,
      "rssi": -63.25
    },
    {
      "sensor_id": "plant1",
      "ts": "2026-03-06 21:00:00",
      "raw": 624.5,
      "moisture": 97.25,
      "vcc": null,
      "rssi": -64.0
    },
    {
      "sensor_id": "plant1",
      "ts": "2026-03-06 22:00:00",
      "raw": 623.5,
      "moisture": 97.0,
      "vcc": null,
      "rssi": -64.25
    },
    {
      "sensor_id": "plant1",
      "ts": "2026-03-06 23:00:00",
      "raw": 624.5,
      "moisture": 97.25,
      "vcc": null,
      "rssi": -64.25
    },
    {
      "sensor_id": "plant1",
      "ts": "2026-03-07 00:00:00",
      "raw": 624.25,
      "moisture": 97.25,
      "vcc": null,
      "rssi": -64.0
    },
    {
      "sensor_id": "plant1",
      "ts": "2026-03-07 01:00:00",
      "raw": 624.25,
      "moisture": 97.0,
      "vcc": null,
      "rssi": -64.0
    },
    {
      "sensor_id": "plant1",
      "ts": "2026-03-07 02:00:00",
      "raw": 624.25,
      "moisture": 97.25,
      "vcc": null,
      "rssi": -63.25
    },
    {
      "sensor_id": "plant1",
      "ts": "2026-03-07 03:00:00",
      "raw": 624.25,
      "moisture": 97.0,
      "vcc": null,
      "rssi": -63.5
    },
    {
      "sensor_id": "plant1",
      "ts": "2026-03-07 04:00:00",
      "raw": 624.5,
      "moisture": 97.25,
      "vcc": null,
      "rssi": -64.25
    },
    {
      "sensor_id": "plant1",
      "ts": "2026-03-07 05:00:00",
      "raw": 643.75,
      "moisture": 98.5,
      "vcc": null,
      "rssi": -64.0
    },
    {
      "sensor_id": "plant1",
      "ts": "2026-03-07 06:00:00",
      "raw": 624.75,
      "moisture": 97.25,
      "vcc": null,
      "rssi": -63.75
    },
    {
      "sensor_id": "plant1",
      "ts": "2026-03-07 07:00:00",
      "raw": 624.75,
      "moisture": 97.25,
      "vcc": null,
      "rssi": -64.0
    },
    {
      "sensor_id": "plant1",
      "ts": "2026-03-07 08:00:00",
      "raw": 625.0,
      "moisture": 97.5,
      "vcc": null,
      "rssi": -64.25
    },
    {
      "sensor_id": "plant1",
      "ts": "2026-03-07 09:00:00",
      "raw": 619.25,
      "moisture": 95.25,
      "vcc": null,
      "rssi": -64.25
    },
    {
      "sensor_id": "plant1",
      "ts": "2026-03-07 10:00:00",
      "raw": 634.0,
      "moisture": 100.0,
      "vcc": null,
      "rssi": -64.75
    },
    {
      "sensor_id": "plant1",
      "ts": "2026-03-07 11:00:00",
      "raw": 633.25,
      "moisture": 100.0,
      "vcc": null,
      "rssi": -65.25
    },
    {
      "sensor_id": "plant1",
      "ts": "2026-03-07 12:00:00",
      "raw": 637.0,
      "moisture": 100.0,
      "vcc": null,
      "rssi": -65.0
    },
    {
      "sensor_id": "plant1",
      "ts": "2026-03-07 13:00:00",
      "raw": 633.75,
      "moisture": 100.0,
      "vcc": null,
      "rssi": -65.0
    },
    {
      "sensor_id": "plant1",
      "ts": "2026-03-07 14:00:00",
      "raw": 633.5,
      "moisture": 99.75,
      "vcc": null,
      "rssi": -65.25
    },
    {
      "sensor_id": "plant1",
      "ts": "2026-03-07 15:00:00",
      "raw": 632.0,
      "moisture": 100.0,
      "vcc": null,
      "rssi": -65.25
    },
    {
      "sensor_id": "plant1",
      "ts": "2026-03-07 16:00:00",
      "raw": 633.75,
      "moisture": 100.0,
      "vcc": null,
      "rssi": -66.0
    },
    {
      "sensor_id": "plant1",
      "ts": "2026-03-07 17:00:00",
      "raw": 633.75,
      "moisture": 100.0,
      "vcc": null,
      "rssi": -65.0
    },
    {
      "sensor_id": "plant1",
      "ts": "2026-03-07 18:00:00",
      "raw": 634.25,
      "moisture": 100.0,
      "vcc": null,
      "rssi": -65.25
    },
    {
      "sensor_id": "plant1",
      "ts": "2026-03-07 19:00:00",
      "raw": 635.5,
      "moisture": 100.0,
      "vcc": null,
      "rssi": -65.0
    },
    {
      "sensor_id": "plant1",
      "ts": "2026-03-07 20:00:00",
      "raw": 637.25,
      "moisture": 100.0,
      "vcc": null,
      "rssi": -65.0
    },
    {
      "sensor_id": "plant1",
      "ts": "2026-03-07 21:00:00",
      "raw": 637.5,
      "moisture": 100.0,
      "vcc": null,
      "rssi": -65.25
    },
    {
      "sensor_id": "plant1",
      "ts": "2026-03-07 22:00:00",
      "raw": 637.25,
      "moisture": 100.0,
      "vcc": null,
      "rssi": -65.0
    },
    {
      "sensor_id": "plant1",
      "ts": "2026-03-07 23:00:00",
      "raw": 639.25,
      "moisture": 100.0,
      "vcc": null,
      "rssi": -65.0
    },
    {
      "sensor_id": "plant1",
      "ts": "2026-03-08 00:00:00",
      "raw": 635.5,
      "moisture": 100.0,
      "vcc": null,
      "rssi": -65.0
    },
    {
      "sensor_id": "plant1",
      "ts": "2026-03-08 01:00:00",
      "raw": 638.25,
      "moisture": 100.0,
      "vcc": null,
      "rssi": -65.0
    },
    {
      "sensor_id": "plant1",
      "ts": "2026-03-08 02:00:00",
      "raw": 637.5,
      "moisture": 100.0,
      "vcc": null,
      "rssi": -64.75
    },
    {
      "sensor_id": "plant1",
      "ts": "2026-03-08 03:00:00",
      "raw": 637.0,
      "moisture": 100.0,
      "vcc": null,
      "rssi": -65.25
    },
    {
      "sensor_id": "plant1",
      "ts": "2026-03-08 04:00:00",
      "raw": 637.25,
      "moisture": 100.0,
      "vcc": null,
      "rssi": -65.0
    },
    {
      "sensor_id": "plant1",
      "ts": "2026-03-08 05:00:00",
      "raw": 637.0,
      "moisture": 100.0,
      "vcc": null,
      "rssi": -65.0
    },
    {
      "sensor_id": "plant1",
      "ts": "2026-03-08 06:00:00",
      "raw": 637.75,
      "moisture": 100.0,
      "vcc": null,
      "rssi": -65.0
    },
    {
      "sensor_id": "plant1",
      "ts": "2026-03-08 07:00:00",
      "raw": 635.5,
      "moisture": 100.0,
      "vcc": null,
      "rssi": -65.0
    },
    {
      "sensor_id": "plant1",
      "ts": "2026-03-08 08:00:00",
      "raw": 633.5,
      "moisture": 100.0,
      "vcc": null,
      "rssi": -65.25
    },
    {
      "sensor_id": "plant1",
      "ts": "2026-03-08 09:00:00",
      "raw": 629.25,
      "moisture": 99.25,
      "vcc": null,
      "rssi": -65.5
    },
    {
      "sensor_id": "plant1",
      "ts": "2026-03-08 10:00:00",
      "raw": 671.75,
      "moisture": 100.0,
      "vcc": null,
      "rssi": -65.5
    },
    {
      "sensor_id": "plant1",
      "ts": "2026-03-08 11:00:00",
      "raw": 633.75,
      "moisture": 100.0,
      "vcc": null,
      "rssi": -65.0
    },
    {
      "sensor_id": "plant1",
      "ts": "2026-03-08 12:00:00",
      "raw": 632.75,
      "moisture": 100.0,
      "vcc": null,
      "rssi": -65.5
    },
    {
      "sensor_id": "plant1",
      "ts": "2026-03-08 13:00:00",
      "raw": 631.25,
      "moisture": 99.75,
      "vcc": null,
      "rssi": -66.0
    },
    {
      "sensor_id": "plant1",
      "ts": "2026-03-08 14:00:00",
      "raw": 631.0,
      "moisture": 100.0,
      "vcc": null,
      "rssi": -65.25
    },
    {
      "sensor_id": "plant1",
      "ts": "2026-03-08 15:00:00",
      "raw": 629.5,
      "moisture": 99.5,
      "vcc": null,
      "rssi": -65.5
    },
    {
      "sensor_id": "plant1",
      "ts": "2026-03-08 16:00:00",
      "raw": 629.75,
      "moisture": 99.5,
      "vcc": null,
      "rssi": -66.25
    },
    {
      "sensor_id": "plant1",
      "ts": "2026-03-08 17:00:00",
      "raw": 627.5,
      "moisture": 98.5,
      "vcc": null,
      "rssi": -65.0
    }
  ]
}